pydsx/README.md
pydsx/__init__.py
pydsx/binary_search_tree/__init__.py
pydsx/binary_search_tree/binary_search_tree.py
pydsx/singly_linked_list/__init__.py
pydsx/singly_linked_list/linked_list.py
pydsx-0.1.0.dist-info/WHEEL
pydsx-0.1.0.dist-info/METADATA
pydsx-0.1.0.dist-info/RECORD
