Metadata-Version: 2.1
Name: pydsx
Version: 0.1.0
Summary: Data structures in python to use in some projects <Matheus Francisco>
Author: matheusfrancisco
Author-email: matheusmachadoufsc@gmail.com
Requires-Python: >=3.8,<4.0
Classifier: Programming Language :: Python :: 3
Classifier: Programming Language :: Python :: 3.8
